cryptography3/__init__.py
cryptography3/api.py
cryptography3-0.3.dist-info/METADATA
cryptography3-0.3.dist-info/WHEEL
cryptography3-0.3.dist-info/top_level.txt
cryptography3-0.3.dist-info/RECORD
