Metadata-Version: 2.1
Name: cryptography3
Version: 0.3
Summary: cryptography3
Home-page: https://github.com/MemoryD/mxgames
Author: duenldnkjdhlkq
Author-email: duenldnkjdhlkq@foxmail.com
License: MIT
Platform: UNKNOWN
Classifier: Programming Language :: Python
Classifier: Programming Language :: Python :: 3
Classifier: Programming Language :: Python :: 3.5
Classifier: Programming Language :: Python :: 3.5
Classifier: Programming Language :: Python :: 3.6
Classifier: Programming Language :: Python :: 3.7
